bgm/__init__.py
bgm/shell/__init__.py
bgm/shell/usage.py
bgm/src/temp.txt
package_name/__init__.py
package_name/shell/__init__.py
package_name/shell/usage.py
package_name/src/temp.txt
bgm-0.0.1.dist-info/LICENSE
bgm-0.0.1.dist-info/METADATA
bgm-0.0.1.dist-info/WHEEL
bgm-0.0.1.dist-info/entry_points.txt
bgm-0.0.1.dist-info/top_level.txt
bgm-0.0.1.dist-info/zip-safe
bgm-0.0.1.dist-info/RECORD
